Workbook

Sheet Synthèse
A1: SYNTHÈSE DE RECETTE CYNA
A2: Indicateurs calculés à partir des lignes du plan de tests. Compléter les statuts avant toute décision de release.
A4: Total | B4: À exécuter | C4: Réussis | D4: Échoués | E4: Bloqués | F4: Non applicables | G4: Taux de réussite | H4: Échecs critiques
A5: =COUNTA('Plan de tests'!A5:A250) | B5: =COUNTIF('Plan de tests'!N5:N250,"À exécuter") | C5: =COUNTIF('Plan de tests'!N5:N250,"Réussi") | D5: =COUNTIF('Plan de tests'!N5:N250,"Échoué") | E5: =COUNTIF('Plan de tests'!N5:N250,"Bloqué") | F5: =COUNTIF('Plan de tests'!N5:N250,"Non applicable") | G5: =IFERROR(C5/(C5+D5),0) | H5: =COUNTIFS('Plan de tests'!F5:F250,"Critique",'Plan de tests'!N5:N250,"Échoué")
A8: Domaine | B8: Total | C8: Réussis | D8: Échoués | E8: Bloqués | F8: À exécuter | H8: Décision | I8: Règle | J8: Valeur
A9: Navigation | B9: =COUNTIF('Plan de tests'!B$5:B$250,A9) | C9: =COUNTIFS('Plan de tests'!B$5:B$250,A9,'Plan de tests'!N$5:N$250,"Réussi") | D9: =COUNTIFS('Plan de tests'!B$5:B$250,A9,'Plan de tests'!N$5:N$250,"Échoué") | E9: =COUNTIFS('Plan de tests'!B$5:B$250,A9,'Plan de tests'!N$5:N$250,"Bloqué") | F9: =COUNTIFS('Plan de tests'!B$5:B$250,A9,'Plan de tests'!N$5:N$250,"À exécuter") | H9: Go | I9: Aucun échec critique et aucun cas critique non exécuté | J9: À valider
A10: Accessibilité | B10: =COUNTIF('Plan de tests'!B$5:B$250,A10) | C10: =COUNTIFS('Plan de tests'!B$5:B$250,A10,'Plan de tests'!N$5:N$250,"Réussi") | D10: =COUNTIFS('Plan de tests'!B$5:B$250,A10,'Plan de tests'!N$5:N$250,"Échoué") | E10: =COUNTIFS('Plan de tests'!B$5:B$250,A10,'Plan de tests'!N$5:N$250,"Bloqué") | F10: =COUNTIFS('Plan de tests'!B$5:B$250,A10,'Plan de tests'!N$5:N$250,"À exécuter") | H10: Go conditionnel | I10: Écarts non critiques acceptés et documentés | J10: À valider
A11: Responsive | B11: =COUNTIF('Plan de tests'!B$5:B$250,A11) | C11: =COUNTIFS('Plan de tests'!B$5:B$250,A11,'Plan de tests'!N$5:N$250,"Réussi") | D11: =COUNTIFS('Plan de tests'!B$5:B$250,A11,'Plan de tests'!N$5:N$250,"Échoué") | E11: =COUNTIFS('Plan de tests'!B$5:B$250,A11,'Plan de tests'!N$5:N$250,"Bloqué") | F11: =COUNTIFS('Plan de tests'!B$5:B$250,A11,'Plan de tests'!N$5:N$250,"À exécuter") | H11: No-go | I11: Au moins un échec critique ou intégrité non garantie | J11: À valider
A12: Authentification | B12: =COUNTIF('Plan de tests'!B$5:B$250,A12) | C12: =COUNTIFS('Plan de tests'!B$5:B$250,A12,'Plan de tests'!N$5:N$250,"Réussi") | D12: =COUNTIFS('Plan de tests'!B$5:B$250,A12,'Plan de tests'!N$5:N$250,"Échoué") | E12: =COUNTIFS('Plan de tests'!B$5:B$250,A12,'Plan de tests'!N$5:N$250,"Bloqué") | F12: =COUNTIFS('Plan de tests'!B$5:B$250,A12,'Plan de tests'!N$5:N$250,"À exécuter") | H12: Responsable | I12: Nom de l'approbateur de release
A13: Catalogue | B13: =COUNTIF('Plan de tests'!B$5:B$250,A13) | C13: =COUNTIFS('Plan de tests'!B$5:B$250,A13,'Plan de tests'!N$5:N$250,"Réussi") | D13: =COUNTIFS('Plan de tests'!B$5:B$250,A13,'Plan de tests'!N$5:N$250,"Échoué") | E13: =COUNTIFS('Plan de tests'!B$5:B$250,A13,'Plan de tests'!N$5:N$250,"Bloqué") | F13: =COUNTIFS('Plan de tests'!B$5:B$250,A13,'Plan de tests'!N$5:N$250,"À exécuter") | H13: Date | I13: Date de la décision
A14: Recherche | B14: =COUNTIF('Plan de tests'!B$5:B$250,A14) | C14: =COUNTIFS('Plan de tests'!B$5:B$250,A14,'Plan de tests'!N$5:N$250,"Réussi") | D14: =COUNTIFS('Plan de tests'!B$5:B$250,A14,'Plan de tests'!N$5:N$250,"Échoué") | E14: =COUNTIFS('Plan de tests'!B$5:B$250,A14,'Plan de tests'!N$5:N$250,"Bloqué") | F14: =COUNTIFS('Plan de tests'!B$5:B$250,A14,'Plan de tests'!N$5:N$250,"À exécuter")
A15: Panier | B15: =COUNTIF('Plan de tests'!B$5:B$250,A15) | C15: =COUNTIFS('Plan de tests'!B$5:B$250,A15,'Plan de tests'!N$5:N$250,"Réussi") | D15: =COUNTIFS('Plan de tests'!B$5:B$250,A15,'Plan de tests'!N$5:N$250,"Échoué") | E15: =COUNTIFS('Plan de tests'!B$5:B$250,A15,'Plan de tests'!N$5:N$250,"Bloqué") | F15: =COUNTIFS('Plan de tests'!B$5:B$250,A15,'Plan de tests'!N$5:N$250,"À exécuter")
A16: Checkout | B16: =COUNTIF('Plan de tests'!B$5:B$250,A16) | C16: =COUNTIFS('Plan de tests'!B$5:B$250,A16,'Plan de tests'!N$5:N$250,"Réussi") | D16: =COUNTIFS('Plan de tests'!B$5:B$250,A16,'Plan de tests'!N$5:N$250,"Échoué") | E16: =COUNTIFS('Plan de tests'!B$5:B$250,A16,'Plan de tests'!N$5:N$250,"Bloqué") | F16: =COUNTIFS('Plan de tests'!B$5:B$250,A16,'Plan de tests'!N$5:N$250,"À exécuter")
A17: Stripe | B17: =COUNTIF('Plan de tests'!B$5:B$250,A17) | C17: =COUNTIFS('Plan de tests'!B$5:B$250,A17,'Plan de tests'!N$5:N$250,"Réussi") | D17: =COUNTIFS('Plan de tests'!B$5:B$250,A17,'Plan de tests'!N$5:N$250,"Échoué") | E17: =COUNTIFS('Plan de tests'!B$5:B$250,A17,'Plan de tests'!N$5:N$250,"Bloqué") | F17: =COUNTIFS('Plan de tests'!B$5:B$250,A17,'Plan de tests'!N$5:N$250,"À exécuter")
A18: Espace client | B18: =COUNTIF('Plan de tests'!B$5:B$250,A18) | C18: =COUNTIFS('Plan de tests'!B$5:B$250,A18,'Plan de tests'!N$5:N$250,"Réussi") | D18: =COUNTIFS('Plan de tests'!B$5:B$250,A18,'Plan de tests'!N$5:N$250,"Échoué") | E18: =COUNTIFS('Plan de tests'!B$5:B$250,A18,'Plan de tests'!N$5:N$250,"Bloqué") | F18: =COUNTIFS('Plan de tests'!B$5:B$250,A18,'Plan de tests'!N$5:N$250,"À exécuter")
A19: Abonnements | B19: =COUNTIF('Plan de tests'!B$5:B$250,A19) | C19: =COUNTIFS('Plan de tests'!B$5:B$250,A19,'Plan de tests'!N$5:N$250,"Réussi") | D19: =COUNTIFS('Plan de tests'!B$5:B$250,A19,'Plan de tests'!N$5:N$250,"Échoué") | E19: =COUNTIFS('Plan de tests'!B$5:B$250,A19,'Plan de tests'!N$5:N$250,"Bloqué") | F19: =COUNTIFS('Plan de tests'!B$5:B$250,A19,'Plan de tests'!N$5:N$250,"À exécuter")
A20: Support | B20: =COUNTIF('Plan de tests'!B$5:B$250,A20) | C20: =COUNTIFS('Plan de tests'!B$5:B$250,A20,'Plan de tests'!N$5:N$250,"Réussi") | D20: =COUNTIFS('Plan de tests'!B$5:B$250,A20,'Plan de tests'!N$5:N$250,"Échoué") | E20: =COUNTIFS('Plan de tests'!B$5:B$250,A20,'Plan de tests'!N$5:N$250,"Bloqué") | F20: =COUNTIFS('Plan de tests'!B$5:B$250,A20,'Plan de tests'!N$5:N$250,"À exécuter")
A21: CynAI | B21: =COUNTIF('Plan de tests'!B$5:B$250,A21) | C21: =COUNTIFS('Plan de tests'!B$5:B$250,A21,'Plan de tests'!N$5:N$250,"Réussi") | D21: =COUNTIFS('Plan de tests'!B$5:B$250,A21,'Plan de tests'!N$5:N$250,"Échoué") | E21: =COUNTIFS('Plan de tests'!B$5:B$250,A21,'Plan de tests'!N$5:N$250,"Bloqué") | F21: =COUNTIFS('Plan de tests'!B$5:B$250,A21,'Plan de tests'!N$5:N$250,"À exécuter")
A22: BackOffice | B22: =COUNTIF('Plan de tests'!B$5:B$250,A22) | C22: =COUNTIFS('Plan de tests'!B$5:B$250,A22,'Plan de tests'!N$5:N$250,"Réussi") | D22: =COUNTIFS('Plan de tests'!B$5:B$250,A22,'Plan de tests'!N$5:N$250,"Échoué") | E22: =COUNTIFS('Plan de tests'!B$5:B$250,A22,'Plan de tests'!N$5:N$250,"Bloqué") | F22: =COUNTIFS('Plan de tests'!B$5:B$250,A22,'Plan de tests'!N$5:N$250,"À exécuter")
A23: Sales | B23: =COUNTIF('Plan de tests'!B$5:B$250,A23) | C23: =COUNTIFS('Plan de tests'!B$5:B$250,A23,'Plan de tests'!N$5:N$250,"Réussi") | D23: =COUNTIFS('Plan de tests'!B$5:B$250,A23,'Plan de tests'!N$5:N$250,"Échoué") | E23: =COUNTIFS('Plan de tests'!B$5:B$250,A23,'Plan de tests'!N$5:N$250,"Bloqué") | F23: =COUNTIFS('Plan de tests'!B$5:B$250,A23,'Plan de tests'!N$5:N$250,"À exécuter")
A24: PDF | B24: =COUNTIF('Plan de tests'!B$5:B$250,A24) | C24: =COUNTIFS('Plan de tests'!B$5:B$250,A24,'Plan de tests'!N$5:N$250,"Réussi") | D24: =COUNTIFS('Plan de tests'!B$5:B$250,A24,'Plan de tests'!N$5:N$250,"Échoué") | E24: =COUNTIFS('Plan de tests'!B$5:B$250,A24,'Plan de tests'!N$5:N$250,"Bloqué") | F24: =COUNTIFS('Plan de tests'!B$5:B$250,A24,'Plan de tests'!N$5:N$250,"À exécuter")
A25: CI/CD | B25: =COUNTIF('Plan de tests'!B$5:B$250,A25) | C25: =COUNTIFS('Plan de tests'!B$5:B$250,A25,'Plan de tests'!N$5:N$250,"Réussi") | D25: =COUNTIFS('Plan de tests'!B$5:B$250,A25,'Plan de tests'!N$5:N$250,"Échoué") | E25: =COUNTIFS('Plan de tests'!B$5:B$250,A25,'Plan de tests'!N$5:N$250,"Bloqué") | F25: =COUNTIFS('Plan de tests'!B$5:B$250,A25,'Plan de tests'!N$5:N$250,"À exécuter")
... A28: Maintenance | B28: =COUNTIF('Plan de tests'!B$5:B$250,A28) | C28: =COUNTIFS('Plan de tests'!B$5:B$250,A28,'Plan de tests'!N$5:N$250,"Réussi") | D28: =COUNTIFS('Plan de tests'!B$5:B$250,A28,'Plan de tests'!N$5:N$250,"Échoué") | E28: =COUNTIFS('Plan de tests'!B$5:B$250,A28,'Plan de tests'!N$5:N$250,"Bloqué") | F28: =COUNTIFS('Plan de tests'!B$5:B$250,A28,'Plan de tests'!N$5:N$250,"À exécuter")

Sheet Plan de tests
A1: PLAN DE TESTS CYNA
A2: Document à compléter pendant la recette. Les cellules blanches sont prévues pour l'exécution, les preuves et les anomalies.
A4: ID | B4: Domaine | C4: Fonctionnalité | D4: Exigence / risque | E4: Type | F4: Priorité | G4: Préconditions | H4: Étapes | I4: Données de test | J4: Résultat attendu | K4: Environnement | L4: Exécuteur | M4: Date | N4: Statut | O4: Résultat obtenu | P4: Anomalie | Q4: Preuve | R4: Commentaires
A5: TC-001 | B5: Navigation | C5: Accueil FR | D5: La page d'accueil française est disponible et cohérente. | E5: Fonctionnel | F5: Haute | G5: Déploiement accessible | H5: 1. Ouvrir /fr. 2. Contrôler en-tête, contenu et pied de page. 3. Ouvrir un lien principal. | I5: URL Netlify | J5: Page sans erreur, textes FR, navigation fonctionnelle. | K5: Preview Netlify | L5: Samuel KAKEZ | M5: 46209 | N5: Réussi | O5: Conforme au résultat attendu.
A6: TC-002 | B6: Navigation | C6: Accueil EN | D6: La locale anglaise affiche les libellés et contenus traduits. | E6: Fonctionnel | F6: Haute | G6: Déploiement accessible | H6: 1. Ouvrir /en. 2. Contrôler les zones principales. 3. Naviguer vers un produit. | I6: Locale en | J6: Aucun mélange FR injustifié, liens conservant /en. | K6: Preview Netlify | L6: Samuel KAKEZ | M6: 46209 | N6: Réussi | O6: Conforme au résultat attendu.
A7: TC-003 | B7: Navigation | C7: Changement de langue | D7: Le sélecteur conserve la page équivalente. | E7: Non-régression | F7: Moyenne | G7: Fiche produit existante dans les deux langues | H7: 1. Ouvrir la fiche FR. 2. Passer en EN. 3. Revenir en FR. | I7: Produit traduit | J7: Même produit et locale correcte après chaque bascule. | K7: Preview Netlify | L7: Samuel KAKEZ | M7: 46209 | N7: Réussi | O7: Conforme au résultat attendu.
A8: TC-004 | B8: Navigation | C8: Liens gérés | D8: Les CTA de l'accueil ne pointent ni vers localhost ni vers une preview obsolète. | E8: Sécurité | F8: Haute | G8: Accueil publié | H8: 1. Inspecter les CTA. 2. Ouvrir chaque lien géré. 3. Contrôler le domaine. | I8: Contenus BackOffice | J8: Liens HTTPS valides vers le domaine attendu. | K8: Production Netlify | L8: Samuel KAKEZ | M8: 46209 | N8: Réussi | O8: Conforme au résultat attendu.
A9: TC-005 | B9: Navigation | C9: Pages légales | D9: Les pages FAQ, à propos, mentions et conditions sont accessibles. | E9: Fonctionnel | F9: Moyenne | G9: Déploiement accessible | H9: 1. Ouvrir chaque lien du pied de page. 2. Contrôler titre et contenu. | I9: FR et EN | J9: Code 200, contenu lisible et locale cohérente. | K9: Preview Netlify | L9: Samuel KAKEZ | M9: 46209 | N9: Réussi | O9: Conforme au résultat attendu.
A10: TC-006 | B10: Navigation | C10: Page inconnue | D10: Une URL inconnue ne révèle pas d'information technique. | E10: Sécurité | F10: Moyenne | G10: Déploiement accessible | H10: 1. Ouvrir une URL inexistante. 2. Examiner l'écran et les journaux navigateur. | I10: /fr/route-inconnue-test | J10: Page d'erreur contrôlée, aucune stack trace ni secret. | K10: Preview Netlify | L10: Samuel KAKEZ | M10: 46209 | N10: Réussi | O10: Conforme au résultat attendu.
A11: TC-007 | B11: Accessibilité | C11: Navigation clavier | D11: Les actions principales sont atteignables et visibles au clavier. | E11: Accessibilité | F11: Haute | G11: Accueil chargé | H11: 1. Utiliser Tab et Maj+Tab. 2. Activer menus et liens avec le clavier. 3. Vérifier le focus. | I11: Sans souris | J11: Ordre logique, focus visible, aucune zone bloquée. | K11: Preview Netlify | L11: Samuel KAKEZ | M11: 46209 | N11: Réussi | O11: Conforme au résultat attendu.
A12: TC-008 | B12: Accessibilité | C12: Zoom 200 % | D12: Le contenu reste lisible sans perte d'action. | E12: Accessibilité | F12: Haute | G12: Navigateur desktop | H12: 1. Régler le zoom à 200 %. 2. Parcourir accueil, fiche, panier et formulaire. | I12: Zoom 200 % | J12: Pas de texte coupé ni de bouton inaccessible. | K12: Preview Netlify | L12: Samuel KAKEZ | M12: 46209 | N12: Réussi | O12: Conforme au résultat attendu.
A13: TC-009 | B13: Responsive | C13: Mobile 360 px | D13: Les parcours publics fonctionnent à 360 px. | E13: Responsive | F13: Haute | G13: Outils responsive | H13: 1. Régler 360 px. 2. Tester menu, recherche, fiche, panier et inscription. | I13: 360 x 800 | J13: Pas de débordement horizontal, actions utilisables. | K13: Preview Netlify | L13: Samuel KAKEZ | M13: 46209 | N13: Réussi | O13: Conforme au résultat attendu.
A14: TC-010 | B14: Responsive | C14: Tablette 768 px | D14: La grille et les formulaires s'adaptent à 768 px. | E14: Responsive | F14: Moyenne | G14: Outils responsive | H14: 1. Régler 768 px. 2. Ouvrir accueil, recherche et dashboard Sales. | I14: 768 x 1024 | J14: Mise en page stable, légendes lisibles. | K14: Preview Netlify | L14: Samuel KAKEZ | M14: 46209 | N14: Réussi | O14: Conforme au résultat attendu.
A15: TC-011 | B15: Responsive | C15: Desktop 1440 px | D15: Les zones larges exploitent l'espace sans étirement nuisible. | E15: Responsive | F15: Moyenne | G15: Outils responsive | H15: 1. Régler 1440 px. 2. Contrôler contenu public et BackOffice. | I15: 1440 x 900 | J15: Alignements cohérents et tableaux exploitables. | K15: Preview Netlify | L15: Samuel KAKEZ | M15: 46210 | N15: Réussi | O15: Conforme au résultat attendu.
A16: TC-012 | B16: Accessibilité | C16: Graphiques Sales | D16: Les graphiques possèdent titres, légendes et résumés textuels. | E16: Accessibilité | F16: Haute | G16: Admin AAL2 et ventes de test | H16: 1. Ouvrir Sales. 2. Naviguer au clavier. 3. Contrôler résumés et infobulles. | I16: 7d et 5w | J16: Informations essentielles disponibles sans dépendre uniquement de la couleur. | K16: Preview Netlify | L16: Samuel KAKEZ | M16: 46210 | N16: Réussi | O16: Conforme au résultat attendu.
... A84: TC-080 | B84: Maintenance | C84: Rollback | D84: Le déploiement précédent peut être restauré puis vérifié. | E84: Exploitation | F84: Haute | G84: Fenêtre de test et déploiement sain connu | H84: 1. Déployer une version sentinelle. 2. Restaurer la précédente. 3. Exécuter le smoke test. | I84: Aucune migration destructive | J84: Code restauré, routes et webhook opérationnels. | K84: Preview Netlify | L84: Samuel KAKEZ | M84: 46216 | N84: Réussi | O84: Conforme au résultat attendu.

Sheet Référentiels
A1: Domaines | B1: Types | C1: Priorités | D1: Environnements | E1: Statuts
A2: Navigation | B2: Fonctionnel | C2: Critique | D2: Local | E2: À exécuter
A3: Accessibilité | B3: Intégration | C3: Haute | D3: Supabase local | E3: Réussi
A4: Responsive | B4: Sécurité | C4: Moyenne | D4: Stripe test | E4: Échoué
A5: Authentification | B5: Accessibilité | C5: Basse | D5: Preview Netlify | E5: Bloqué
A6: Catalogue | B6: Responsive | D6: Production Netlify | E6: Non applicable
A7: Recherche | B7: Non-régression
A8: Panier | B8: Exploitation
A9: Checkout
A10: Stripe
A11: Espace client
A12: Abonnements
A13: Support
A14: CynAI
A15: BackOffice
A16: Sales
A17: PDF
A18: CI/CD
A19: Netlify
A20: Sentry
A21: Maintenance

Sheet Mode d'emploi
A1: MODE D'EMPLOI DU PLAN DE TESTS
A3: Champ | B3: Consigne | D3: Rôle | E3: Responsabilité | F3: Validation
A4: Portée | B4: Dupliquer ou ajouter une ligne pour chaque variante utile. Ne jamais remplacer un cas existant par un résultat sans conserver l'exigence. | D4: Recetteur | E4: Exécuter et documenter les cas | F4: Résultat observable et preuve
A5: Préparation | B5: Utiliser des comptes, produits et paiements de test. Ne jamais inscrire de secret, mot de passe, code MFA ou numéro de carte réel dans le classeur. | D5: Développeur | E5: Analyser et corriger les anomalies | F5: Tests automatisés et non-régression
A6: Exécution | B6: Renseigner Exécuteur, Date, Statut et Résultat obtenu. Noter les valeurs observées, pas seulement conforme ou non conforme. | D6: Product Owner | E6: Accepter le comportement métier | F6: Critères d'acceptation
A7: Anomalie | B7: Inscrire l'identifiant du ticket GitHub ou du suivi choisi. Une anomalie critique bloque la recette tant qu'elle n'est pas corrigée ou acceptée formellement. | D7: Responsable release | E7: Prendre la décision go/no-go | F7: Synthèse, CI, preview et rollback
A8: Preuve | B8: Ajouter un chemin de capture, un lien de rapport ou un identifiant de log expurgé. Ne pas coller de données personnelles.
A9: Rejeu | B9: Après correction, conserver le résultat précédent dans Commentaires et dater le nouveau passage.
A10: Production | B10: Limiter la production aux smoke tests sûrs. Les tests destructifs, signatures invalides, seeds et paiements de laboratoire restent sur Local ou Preview.
A11: Synthèse | B11: La feuille Synthèse se met à jour à partir des statuts de la feuille Plan de tests.
A12: Validation finale | B12: Exiger zéro échec critique, expliquer les cas bloqués et faire approuver le périmètre par le responsable de recette.
